snowleopard/__init__.py
snowleopard/async_client.py
snowleopard/cli.py
snowleopard/client.py
snowleopard/client_base.py
snowleopard/models.py
snowleopard-0.2.0.dist-info/METADATA
snowleopard-0.2.0.dist-info/WHEEL
snowleopard-0.2.0.dist-info/entry_points.txt
snowleopard-0.2.0.dist-info/licenses/LICENSE
snowleopard-0.2.0.dist-info/RECORD
