Metadata-Version: 2.4
Name: snowleopard
Version: 0.2.0
Summary: snowleopard.ai client library
Author-email: Snowy <hello@snowleopard.ai>
License: MIT License
License-File: LICENSE
Classifier: Development Status :: 2 - Pre-Alpha
Classifier: Environment :: Console
Classifier: Intended Audience :: Developers
Requires-Python: >=3.8
Requires-Dist: httpx>=0.28.1
